odoo10_addon_web_send_message_popup-10.0.1.0.0-py2.7-nspkg.pth
odoo10_addon_web_send_message_popup-10.0.1.0.0.dist-info/top_level.txt
odoo10_addon_web_send_message_popup-10.0.1.0.0.dist-info/WHEEL
odoo10_addon_web_send_message_popup-10.0.1.0.0.dist-info/RECORD
odoo10_addon_web_send_message_popup-10.0.1.0.0.dist-info/metadata.json
odoo10_addon_web_send_message_popup-10.0.1.0.0.dist-info/DESCRIPTION.rst
odoo10_addon_web_send_message_popup-10.0.1.0.0.dist-info/METADATA
odoo10_addon_web_send_message_popup-10.0.1.0.0.dist-info/namespace_packages.txt
odoo/addons/web_send_message_popup/__manifest__.py
odoo/addons/web_send_message_popup/__init__.py
odoo/addons/web_send_message_popup/README.rst
odoo/addons/web_send_message_popup/views/web_send_message_popup.xml
odoo/addons/web_send_message_popup/static/src/js/chatter.js
